LICENSE
MANIFEST.in
README.md
setup.cfg
setup.py
features/__init__.py
features/base.py
features/exceptions.py
features/manager.py
features/models.py
features/signals.py
features/urls.py
features/views.py
features/migrations/0001_initial.py
features/migrations/__init__.py
features/templatetags/__init__.py
features/templatetags/features.py
podiant_features.egg-info/PKG-INFO
podiant_features.egg-info/SOURCES.txt
podiant_features.egg-info/dependency_links.txt
podiant_features.egg-info/not-zip-safe
podiant_features.egg-info/top_level.txt